LICENSE
MANIFEST.in
README.md
VERSION
requirements.txt
setup.py
setup_utils.py
src/gai/cli/__init__.py
src/gai/cli/main.py
src/gai/cli/_gai_cli/Init.py
src/gai/cli/_gai_cli/MultilineInputCmd.py
src/gai/cli/_gai_cli/Tools.py
src/gai/cli/scripts/docker-compose.yml
src/gai/cli/scripts/gai_docker_start.py
src/gai/cli/scripts/gai_docker_stop.py
src/gai/cli/scripts/gai_init.py
src/gai/cli/scripts/gai_news.py
src/gai/cli/scripts/gai_pull.py
src/gai/cli/scripts/gai_search.py
src/gai/cli/scripts/main.py
src/gai_cli.egg-info/PKG-INFO
src/gai_cli.egg-info/SOURCES.txt
src/gai_cli.egg-info/dependency_links.txt
src/gai_cli.egg-info/entry_points.txt
src/gai_cli.egg-info/requires.txt
src/gai_cli.egg-info/top_level.txt