Metadata-Version: 2.1
Name: gai-cli
Version: 0.187
Summary: Refer to https://gai-labs.github.io/gai for more information
Author: kakkoii1337
Author-email: kakkoii1337@gmail.com
Classifier: Programming Language :: Python :: 3.10
Classifier: Development Status :: 3 - Alpha
Classifier: License :: OSI Approved :: MIT License
Classifier: Intended Audience :: Science/Research
Classifier: Intended Audience :: Developers
Classifier: Operating System :: OS Independent
Classifier: Topic :: Software Development
Classifier: Topic :: Software Development :: Libraries :: Python Modules
Classifier: Topic :: Scientific/Engineering :: Artificial Intelligence
Requires-Python: >=3.10
License-File: LICENSE
Requires-Dist: pytest
Requires-Dist: ipykernel
Requires-Dist: gai-lib
Requires-Dist: pynvml
Requires-Dist: gai-ttt
Requires-Dist: nats-py
